chardet/__init__.py
chardet/big5freq.py
chardet/big5prober.py
chardet/chardistribution.py
chardet/charsetgroupprober.py
chardet/charsetprober.py
chardet/codingstatemachine.py
chardet/compat.py
chardet/cp949prober.py
chardet/enums.py
chardet/escprober.py
chardet/escsm.py
chardet/eucjpprober.py
chardet/euckrfreq.py
chardet/euckrprober.py
chardet/euctwfreq.py
chardet/euctwprober.py
chardet/gb2312freq.py
chardet/gb2312prober.py
chardet/hebrewprober.py
chardet/jisfreq.py
chardet/jpcntx.py
chardet/langbulgarianmodel.py
chardet/langcyrillicmodel.py
chardet/langgreekmodel.py
chardet/langhebrewmodel.py
chardet/langhungarianmodel.py
chardet/langthaimodel.py
chardet/langturkishmodel.py
chardet/latin1prober.py
chardet/mbcharsetprober.py
chardet/mbcsgroupprober.py
chardet/mbcssm.py
chardet/sbcharsetprober.py
chardet/sbcsgroupprober.py
chardet/sjisprober.py
chardet/universaldetector.py
chardet/utf8prober.py
chardet/version.py
chardet/cli/__init__.py
chardet/cli/chardetect.py
chardet-3.0.1.dist-info/DESCRIPTION.rst
chardet-3.0.1.dist-info/METADATA
chardet-3.0.1.dist-info/RECORD
chardet-3.0.1.dist-info/WHEEL
chardet-3.0.1.dist-info/entry_points.txt
chardet-3.0.1.dist-info/metadata.json
chardet-3.0.1.dist-info/top_level.txt
